{
  "generated_at": "2026-06-28T08:29:01.531Z",
  "period": "last_7_days",
  "source_files": {
    "shopify": "shopify_orders_last_7_days.json",
    "google_ads": "google_ads_last_7_days.json",
    "bol_enriched": "bol_enriched_last_7_days.json",
    "bol_ads": "bol_ads_last_7_days.json"
  },
  "warnings": [],
  "cost_lookup": {
    "entries": 13,
    "source": "Shopify inventoryItem.unitCost, fallback config/product_costs.json",
    "shopify_entries": 76,
    "shopify_with_unit_cost": 57,
    "legacy_excel_entries": 1,
    "note": "Cost order: Shopify Cost per item, config/product_costs.json, then missing."
  },
  "totals": {
    "orders": 17,
    "betrouwbare_orders": 16,
    "onvolledige_orders": 1,
    "orders_met_shopify_kostprijs": 16,
    "orders_met_fallback_kostprijs": 0,
    "orders_zonder_kostprijs": 1,
    "omzet": 452.76,
    "verzendkosten_betaald_door_klant": 55.75,
    "werkelijke_verzendkosten": 106.51,
    "productkostprijs": 102.09,
    "bruto_winst": 244.16,
    "bol_commissie": 27.66,
    "advertentiekosten": 26.4,
    "bol_advertentiekosten": 10.72,
    "nettowinst": 179.38,
    "betrouwbare_nettowinst": 152.37,
    "geschatte_onvolledige_nettowinst": 27.01,
    "nettowinst_pct": 39.62,
    "betrouwbare_nettowinst_pct": 33.65,
    "betrouwbare_orders_pct": 94.12,
    "betrouwbare_winst_pct": 84.94,
    "winst_betrouwbaarheid": "gedeeltelijk betrouwbaar",
    "gemiddelde_winst_per_order": 10.55,
    "google_ads_cost_total": 26.4,
    "google_ads_unallocated": 0,
    "google_ads_roas": 0.553,
    "bol_ads_cost_total": 10.72,
    "bol_ads_unallocated": 0,
    "bol_ads_roas": 0.9832,
    "bol_ads_supported": true
  },
  "channel_totals": {
    "Shopify direct": {
      "orders": 5,
      "omzet": 141.02,
      "werkelijke_verzendkosten": 34.84,
      "productkostprijs": 30.9,
      "bol_commissie": 0,
      "advertentiekosten": 20.57,
      "bol_advertentiekosten": 0,
      "nettowinst": 54.71,
      "betrouwbare_nettowinst": 27.7,
      "geschatte_onvolledige_nettowinst": 27.01,
      "betrouwbare_orders": 4,
      "onvolledige_orders": 1,
      "orders_met_shopify_kostprijs": 4,
      "orders_met_fallback_kostprijs": 0,
      "orders_zonder_kostprijs": 1,
      "nettowinst_pct": 38.8
    },
    "Bol via Shopify": {
      "orders": 11,
      "omzet": 271.8,
      "werkelijke_verzendkosten": 59.57,
      "productkostprijs": 67.32,
      "bol_commissie": 27.66,
      "advertentiekosten": 0,
      "bol_advertentiekosten": 10.72,
      "nettowinst": 106.53,
      "betrouwbare_nettowinst": 106.53,
      "geschatte_onvolledige_nettowinst": 0,
      "betrouwbare_orders": 11,
      "onvolledige_orders": 0,
      "orders_met_shopify_kostprijs": 11,
      "orders_met_fallback_kostprijs": 0,
      "orders_zonder_kostprijs": 0,
      "nettowinst_pct": 39.19
    },
    "Onbekend/overig": {
      "orders": 1,
      "omzet": 39.94,
      "werkelijke_verzendkosten": 12.1,
      "productkostprijs": 3.87,
      "bol_commissie": 0,
      "advertentiekosten": 5.83,
      "bol_advertentiekosten": 0,
      "nettowinst": 18.14,
      "betrouwbare_nettowinst": 18.14,
      "geschatte_onvolledige_nettowinst": 0,
      "betrouwbare_orders": 1,
      "onvolledige_orders": 0,
      "orders_met_shopify_kostprijs": 1,
      "orders_met_fallback_kostprijs": 0,
      "orders_zonder_kostprijs": 0,
      "nettowinst_pct": 45.42
    }
  },
  "bol": {
    "matched_orders": 11,
    "missing_in_shopify": 0,
    "ads_supported": true
  },
  "orders": [
    {
      "order_number": "#3dts1645",
      "date": "2026-06-22T11:28:32Z",
      "channel_source": "web",
      "channel": "Shopify direct",
      "channel_reason": "shopify_source_web",
      "customer_country_code": "NL",
      "customer_country": "Netherlands",
      "tags": [],
      "payment_status": "PAID",
      "fulfillment_status": "FULFILLED",
      "landing_site": null,
      "referring_site": null,
      "omzet": 50.62,
      "verzendkosten_betaald_door_klant": 7.1,
      "verzendopbrengst_uit_pseudo_producten": 0,
      "werkelijke_verzendkosten": 5.6,
      "productkostprijs": 10.63,
      "korting": 4.83,
      "bruto_winst": 34.39,
      "bol_commissie": 0,
      "advertentiekosten": 7.38,
      "advertentiekosten_methode": "allocated_by_order_revenue_share",
      "bol_advertentiekosten": 0,
      "bol_advertentiekosten_methode": "none",
      "nettowinst": 27.01,
      "betrouwbare_nettowinst": null,
      "geschatte_onvolledige_nettowinst": 27.01,
      "profit_reliability": "incomplete",
      "cost_coverage": "missing",
      "nettowinst_pct": 53.36,
      "bol_order_id": null,
      "bol_match_method": null,
      "bol_match_confidence": null,
      "eans": [],
      "line_items": [
        {
          "product_name": "HBM 20V Accuhouder – 2-voudig (Wandmontage)",
          "variant_id": "62909492887901",
          "sku": "629094928879_BD5D",
          "ean": "8721516390424",
          "quantity": 2,
          "item_type": "product",
          "product_sale_price": 11.95,
          "line_revenue": 23.9,
          "product_cost_unit": 0,
          "product_cost_total": 0,
          "gross_profit_before_shipping_ads": 23.9,
          "margin_before_shipping_ads_pct": 100,
          "cost_source": "product_costs_json",
          "cost_status": "zero_cost",
          "cost_match_key": "629094928879_BD5D"
        },
        {
          "product_name": "Accuhouder Makita 18V – Wandmontage - 4-voudig",
          "variant_id": "57872304963933",
          "sku": "Makita4v3dts.shop",
          "ean": "8721516390097",
          "quantity": 1,
          "item_type": "product",
          "product_sale_price": 12.5,
          "line_revenue": 12.5,
          "product_cost_unit": 6.33,
          "product_cost_total": 6.33,
          "gross_profit_before_shipping_ads": 6.17,
          "margin_before_shipping_ads_pct": 49.36,
          "cost_source": "shopify_unit_cost",
          "cost_status": "matched",
          "cost_match_key": "57872304963933"
        },
        {
          "product_name": "Wandhouder voor Makita DC18RD Duo Oplader – 3D Geprint – Compatibel met 18V Laadstation",
          "variant_id": "58085095440733",
          "sku": "dc18rd3dts.shop",
          "ean": "8721516390004",
          "quantity": 1,
          "item_type": "product",
          "product_sale_price": 11.95,
          "line_revenue": 11.95,
          "product_cost_unit": 4.3,
          "product_cost_total": 4.3,
          "gross_profit_before_shipping_ads": 7.65,
          "margin_before_shipping_ads_pct": 64.02,
          "cost_source": "shopify_unit_cost",
          "cost_status": "matched",
          "cost_match_key": "58085095440733"
        }
      ],
      "cost_sources": [
        "shopify_unit_cost"
      ],
      "warnings": [
        "product_cost_missing",
        "profit_incomplete",
        "ad_cost_allocated_by_revenue_share"
      ]
    },
    {
      "order_number": "#3dts1646",
      "date": "2026-06-22T15:10:08Z",
      "channel_source": "bol",
      "channel": "Bol via Shopify",
      "channel_reason": "matched_bol_retailer_api",
      "customer_country_code": "BE",
      "customer_country": "Belgium",
      "tags": [
        "bol.com"
      ],
      "payment_status": "PAID",
      "fulfillment_status": "FULFILLED",
      "landing_site": null,
      "referring_site": null,
      "omzet": 17.34,
      "verzendkosten_betaald_door_klant": 0,
      "verzendopbrengst_uit_pseudo_producten": 0,
      "werkelijke_verzendkosten": 8.09,
      "productkostprijs": 4.3,
      "korting": 0,
      "bruto_winst": 4.95,
      "bol_commissie": 3.08,
      "advertentiekosten": 0,
      "advertentiekosten_methode": "none",
      "bol_advertentiekosten": 0.68,
      "bol_advertentiekosten_methode": "allocated_by_bol_order_revenue_share",
      "nettowinst": 1.19,
      "betrouwbare_nettowinst": 1.19,
      "geschatte_onvolledige_nettowinst": 0,
      "profit_reliability": "reliable",
      "cost_coverage": "shopify",
      "nettowinst_pct": 6.86,
      "bol_order_id": "C00076MJ1J",
      "bol_match_method": "date_amount_country_product_fallback",
      "bol_match_confidence": 0.9,
      "eans": [
        "9509658425575"
      ],
      "line_items": [
        {
          "product_name": "Wandhouder voor Makita DC18RD Duo Oplader – 3D Geprint – Compatibel met 18V Laadstation",
          "variant_id": "58085095440733",
          "sku": "dc18rd3dts.shop",
          "ean": "8721516390004",
          "quantity": 1,
          "item_type": "product",
          "product_sale_price": 17.34,
          "line_revenue": 17.34,
          "product_cost_unit": 4.3,
          "product_cost_total": 4.3,
          "gross_profit_before_shipping_ads": 13.04,
          "margin_before_shipping_ads_pct": 75.2,
          "cost_source": "shopify_unit_cost",
          "cost_status": "matched",
          "cost_match_key": "58085095440733"
        }
      ],
      "cost_sources": [
        "shopify_unit_cost"
      ],
      "warnings": [
        "bol_ads_allocated_by_bol_revenue_share"
      ]
    },
    {
      "order_number": "#3dts1647",
      "date": "2026-06-22T19:25:07Z",
      "channel_source": "bol",
      "channel": "Bol via Shopify",
      "channel_reason": "matched_bol_retailer_api",
      "customer_country_code": "NL",
      "customer_country": "Netherlands",
      "tags": [
        "bol.com"
      ],
      "payment_status": "PAID",
      "fulfillment_status": "FULFILLED",
      "landing_site": null,
      "referring_site": null,
      "omzet": 11.95,
      "verzendkosten_betaald_door_klant": 0,
      "verzendopbrengst_uit_pseudo_producten": 0,
      "werkelijke_verzendkosten": 3.7,
      "productkostprijs": 3.07,
      "korting": 0,
      "bruto_winst": 5.18,
      "bol_commissie": 0.84,
      "advertentiekosten": 0,
      "advertentiekosten_methode": "none",
      "bol_advertentiekosten": 0.47,
      "bol_advertentiekosten_methode": "allocated_by_bol_order_revenue_share",
      "nettowinst": 3.87,
      "betrouwbare_nettowinst": 3.87,
      "geschatte_onvolledige_nettowinst": 0,
      "profit_reliability": "reliable",
      "cost_coverage": "shopify",
      "nettowinst_pct": 32.38,
      "bol_order_id": "C000775DHH",
      "bol_match_method": "identifier_or_sku_tag_source",
      "bol_match_confidence": 0.95,
      "eans": [
        "8721516390615"
      ],
      "line_items": [
        {
          "product_name": "UniFi Cloud Key Gen2 Plus Verhoogde Wallmount",
          "variant_id": "63992391369053",
          "sku": "cloudkeygen23DTS.SHOP",
          "ean": "8721516390615",
          "quantity": 1,
          "item_type": "product",
          "product_sale_price": 11.95,
          "line_revenue": 11.95,
          "product_cost_unit": 3.07,
          "product_cost_total": 3.07,
          "gross_profit_before_shipping_ads": 8.88,
          "margin_before_shipping_ads_pct": 74.31,
          "cost_source": "shopify_unit_cost",
          "cost_status": "matched",
          "cost_match_key": "63992391369053"
        }
      ],
      "cost_sources": [
        "shopify_unit_cost"
      ],
      "warnings": [
        "bol_ads_allocated_by_bol_revenue_share"
      ]
    },
    {
      "order_number": "#3dts1648",
      "date": "2026-06-23T09:23:03Z",
      "channel_source": "web",
      "channel": "Shopify direct",
      "channel_reason": "shopify_source_web",
      "customer_country_code": "NL",
      "customer_country": "Netherlands",
      "tags": [],
      "payment_status": "PAID",
      "fulfillment_status": "FULFILLED",
      "landing_site": "https://3dts.shop/products/wandhouder-schuin-voor-makita-dc18rd-duo-oplader-3d-geprint-compatibel-met-18v-laadstation",
      "referring_site": null,
      "omzet": 31,
      "verzendkosten_betaald_door_klant": 7.1,
      "verzendopbrengst_uit_pseudo_producten": 0,
      "werkelijke_verzendkosten": 5.6,
      "productkostprijs": 8.6,
      "korting": 0,
      "bruto_winst": 16.8,
      "bol_commissie": 0,
      "advertentiekosten": 4.52,
      "advertentiekosten_methode": "allocated_by_order_revenue_share",
      "bol_advertentiekosten": 0,
      "bol_advertentiekosten_methode": "none",
      "nettowinst": 12.28,
      "betrouwbare_nettowinst": 12.28,
      "geschatte_onvolledige_nettowinst": 0,
      "profit_reliability": "reliable",
      "cost_coverage": "shopify",
      "nettowinst_pct": 39.61,
      "bol_order_id": null,
      "bol_match_method": null,
      "bol_match_confidence": null,
      "eans": [],
      "line_items": [
        {
          "product_name": "Wandhouder voor Makita DC18RD Duo Oplader – 3D Geprint – Compatibel met 18V Laadstation",
          "variant_id": "58085095440733",
          "sku": "dc18rd3dts.shop",
          "ean": "8721516390004",
          "quantity": 2,
          "item_type": "product",
          "product_sale_price": 11.95,
          "line_revenue": 23.9,
          "product_cost_unit": 4.3,
          "product_cost_total": 8.6,
          "gross_profit_before_shipping_ads": 15.3,
          "margin_before_shipping_ads_pct": 64.02,
          "cost_source": "shopify_unit_cost",
          "cost_status": "matched",
          "cost_match_key": "58085095440733"
        }
      ],
      "cost_sources": [
        "shopify_unit_cost"
      ],
      "warnings": [
        "ad_cost_allocated_by_revenue_share"
      ]
    },
    {
      "order_number": "#3dts1649",
      "date": "2026-06-23T09:45:56Z",
      "channel_source": "bol",
      "channel": "Bol via Shopify",
      "channel_reason": "matched_bol_retailer_api",
      "customer_country_code": "BE",
      "customer_country": "Belgium",
      "tags": [
        "bol.com"
      ],
      "payment_status": "PAID",
      "fulfillment_status": "FULFILLED",
      "landing_site": null,
      "referring_site": null,
      "omzet": 14.66,
      "verzendkosten_betaald_door_klant": 0,
      "verzendopbrengst_uit_pseudo_producten": 0,
      "werkelijke_verzendkosten": 8.09,
      "productkostprijs": 4.3,
      "korting": 0,
      "bruto_winst": 2.27,
      "bol_commissie": 0.92,
      "advertentiekosten": 0,
      "advertentiekosten_methode": "none",
      "bol_advertentiekosten": 0.58,
      "bol_advertentiekosten_methode": "allocated_by_bol_order_revenue_share",
      "nettowinst": 0.77,
      "betrouwbare_nettowinst": 0.77,
      "geschatte_onvolledige_nettowinst": 0,
      "profit_reliability": "reliable",
      "cost_coverage": "shopify",
      "nettowinst_pct": 5.25,
      "bol_order_id": "C00077W384",
      "bol_match_method": "identifier_or_sku_tag_source",
      "bol_match_confidence": 0.95,
      "eans": [
        "8721516390592"
      ],
      "line_items": [
        {
          "product_name": "UniFi Access Point Wandbeugel – Verstelbare / Kantelbare Mount – Geschikt voor UAP-AC-LR, U6-LR, U6-Lite & U7-Lite",
          "variant_id": "63739025588573",
          "sku": "Unifikant3DTS.shop",
          "ean": "8721516390592",
          "quantity": 1,
          "item_type": "product",
          "product_sale_price": 14.66,
          "line_revenue": 14.66,
          "product_cost_unit": 4.3,
          "product_cost_total": 4.3,
          "gross_profit_before_shipping_ads": 10.36,
          "margin_before_shipping_ads_pct": 70.67,
          "cost_source": "shopify_unit_cost",
          "cost_status": "matched",
          "cost_match_key": "63739025588573"
        }
      ],
      "cost_sources": [
        "shopify_unit_cost"
      ],
      "warnings": [
        "bol_ads_allocated_by_bol_revenue_share"
      ]
    },
    {
      "order_number": "#3dts1650",
      "date": "2026-06-23T10:30:58Z",
      "channel_source": "bol",
      "channel": "Bol via Shopify",
      "channel_reason": "matched_bol_retailer_api",
      "customer_country_code": "NL",
      "customer_country": "Netherlands",
      "tags": [
        "bol.com"
      ],
      "payment_status": "PAID",
      "fulfillment_status": "FULFILLED",
      "landing_site": null,
      "referring_site": null,
      "omzet": 88.2,
      "verzendkosten_betaald_door_klant": 0,
      "verzendopbrengst_uit_pseudo_producten": 0,
      "werkelijke_verzendkosten": 3.7,
      "productkostprijs": 21.78,
      "korting": 0,
      "bruto_winst": 62.72,
      "bol_commissie": 5.55,
      "advertentiekosten": 0,
      "advertentiekosten_methode": "none",
      "bol_advertentiekosten": 3.48,
      "bol_advertentiekosten_methode": "allocated_by_bol_order_revenue_share",
      "nettowinst": 53.69,
      "betrouwbare_nettowinst": 53.69,
      "geschatte_onvolledige_nettowinst": 0,
      "profit_reliability": "reliable",
      "cost_coverage": "shopify",
      "nettowinst_pct": 60.87,
      "bol_order_id": "C000673CJH",
      "bol_match_method": "identifier_or_sku_tag_source",
      "bol_match_confidence": 0.95,
      "eans": [
        "8721516390073"
      ],
      "line_items": [
        {
          "product_name": "UniFi Access Point Stand – Bureau Standaard voor U6-LR, U6+, U7 Pro & AC-Pro (PETG, 3D-geprint)",
          "variant_id": "63433470476637",
          "sku": "Unifidesk3DTS.Shop",
          "ean": "8721516390073",
          "quantity": 6,
          "item_type": "product",
          "product_sale_price": 14.7,
          "line_revenue": 88.2,
          "product_cost_unit": 3.63,
          "product_cost_total": 21.78,
          "gross_profit_before_shipping_ads": 66.42,
          "margin_before_shipping_ads_pct": 75.31,
          "cost_source": "shopify_unit_cost",
          "cost_status": "matched",
          "cost_match_key": "63433470476637"
        }
      ],
      "cost_sources": [
        "shopify_unit_cost"
      ],
      "warnings": [
        "bol_ads_allocated_by_bol_revenue_share"
      ]
    },
    {
      "order_number": "#3dts1651",
      "date": "2026-06-23T13:55:57Z",
      "channel_source": "bol",
      "channel": "Bol via Shopify",
      "channel_reason": "matched_bol_retailer_api",
      "customer_country_code": "BE",
      "customer_country": "Belgium",
      "tags": [
        "bol.com"
      ],
      "payment_status": "PAID",
      "fulfillment_status": "FULFILLED",
      "landing_site": null,
      "referring_site": null,
      "omzet": 18.54,
      "verzendkosten_betaald_door_klant": 0,
      "verzendopbrengst_uit_pseudo_producten": 0,
      "werkelijke_verzendkosten": 8.09,
      "productkostprijs": 2,
      "korting": 0,
      "bruto_winst": 8.45,
      "bol_commissie": 3.26,
      "advertentiekosten": 0,
      "advertentiekosten_methode": "none",
      "bol_advertentiekosten": 0.73,
      "bol_advertentiekosten_methode": "allocated_by_bol_order_revenue_share",
      "nettowinst": 4.46,
      "betrouwbare_nettowinst": 4.46,
      "geschatte_onvolledige_nettowinst": 0,
      "profit_reliability": "reliable",
      "cost_coverage": "shopify",
      "nettowinst_pct": 24.06,
      "bol_order_id": "C0007865CM",
      "bol_match_method": "date_amount_country_product_fallback",
      "bol_match_confidence": 0.9,
      "eans": [
        "9509192768565"
      ],
      "line_items": [
        {
          "product_name": "Accuhouder Parkside 20V - 4-voudig",
          "variant_id": "62962109153629",
          "sku": "629621091536_60CB",
          "ean": "8721516390431",
          "quantity": 1,
          "item_type": "product",
          "product_sale_price": 18.54,
          "line_revenue": 18.54,
          "product_cost_unit": 2,
          "product_cost_total": 2,
          "gross_profit_before_shipping_ads": 16.54,
          "margin_before_shipping_ads_pct": 89.21,
          "cost_source": "shopify_unit_cost",
          "cost_status": "matched",
          "cost_match_key": "62962109153629"
        }
      ],
      "cost_sources": [
        "shopify_unit_cost"
      ],
      "warnings": [
        "bol_ads_allocated_by_bol_revenue_share"
      ]
    },
    {
      "order_number": "#3dts1652",
      "date": "2026-06-24T12:40:09Z",
      "channel_source": "bol",
      "channel": "Bol via Shopify",
      "channel_reason": "matched_bol_retailer_api",
      "customer_country_code": "NL",
      "customer_country": "Netherlands",
      "tags": [
        "bol.com"
      ],
      "payment_status": "PAID",
      "fulfillment_status": "FULFILLED",
      "landing_site": null,
      "referring_site": null,
      "omzet": 29.32,
      "verzendkosten_betaald_door_klant": 0,
      "verzendopbrengst_uit_pseudo_producten": 0,
      "werkelijke_verzendkosten": 5.6,
      "productkostprijs": 8.6,
      "korting": 0,
      "bruto_winst": 15.12,
      "bol_commissie": 1.85,
      "advertentiekosten": 0,
      "advertentiekosten_methode": "none",
      "bol_advertentiekosten": 1.16,
      "bol_advertentiekosten_methode": "allocated_by_bol_order_revenue_share",
      "nettowinst": 12.11,
      "betrouwbare_nettowinst": 12.11,
      "geschatte_onvolledige_nettowinst": 0,
      "profit_reliability": "reliable",
      "cost_coverage": "shopify",
      "nettowinst_pct": 41.3,
      "bol_order_id": "C0007C0W73",
      "bol_match_method": "identifier_or_sku_tag_source",
      "bol_match_confidence": 0.95,
      "eans": [
        "8721516390592"
      ],
      "line_items": [
        {
          "product_name": "UniFi Access Point Wandbeugel – Verstelbare / Kantelbare Mount – Geschikt voor UAP-AC-LR, U6-LR, U6-Lite & U7-Lite",
          "variant_id": "63739025588573",
          "sku": "Unifikant3DTS.shop",
          "ean": "8721516390592",
          "quantity": 2,
          "item_type": "product",
          "product_sale_price": 14.66,
          "line_revenue": 29.32,
          "product_cost_unit": 4.3,
          "product_cost_total": 8.6,
          "gross_profit_before_shipping_ads": 20.72,
          "margin_before_shipping_ads_pct": 70.67,
          "cost_source": "shopify_unit_cost",
          "cost_status": "matched",
          "cost_match_key": "63739025588573"
        }
      ],
      "cost_sources": [
        "shopify_unit_cost"
      ],
      "warnings": [
        "bol_ads_allocated_by_bol_revenue_share"
      ]
    },
    {
      "order_number": "#3dts1653",
      "date": "2026-06-24T15:16:13Z",
      "channel_source": "bol",
      "channel": "Bol via Shopify",
      "channel_reason": "matched_bol_retailer_api",
      "customer_country_code": "NL",
      "customer_country": "Netherlands",
      "tags": [
        "bol.com"
      ],
      "payment_status": "PAID",
      "fulfillment_status": "FULFILLED",
      "landing_site": null,
      "referring_site": null,
      "omzet": 17.34,
      "verzendkosten_betaald_door_klant": 0,
      "verzendopbrengst_uit_pseudo_producten": 0,
      "werkelijke_verzendkosten": 5.6,
      "productkostprijs": 4.3,
      "korting": 0,
      "bruto_winst": 7.44,
      "bol_commissie": 3.08,
      "advertentiekosten": 0,
      "advertentiekosten_methode": "none",
      "bol_advertentiekosten": 0.68,
      "bol_advertentiekosten_methode": "allocated_by_bol_order_revenue_share",
      "nettowinst": 3.68,
      "betrouwbare_nettowinst": 3.68,
      "geschatte_onvolledige_nettowinst": 0,
      "profit_reliability": "reliable",
      "cost_coverage": "shopify",
      "nettowinst_pct": 21.22,
      "bol_order_id": "C0007C97MC",
      "bol_match_method": "date_amount_country_product_fallback",
      "bol_match_confidence": 0.9,
      "eans": [
        "9509658425575"
      ],
      "line_items": [
        {
          "product_name": "Wandhouder voor Makita DC18RD Duo Oplader – 3D Geprint – Compatibel met 18V Laadstation",
          "variant_id": "58085095440733",
          "sku": "dc18rd3dts.shop",
          "ean": "8721516390004",
          "quantity": 1,
          "item_type": "product",
          "product_sale_price": 17.34,
          "line_revenue": 17.34,
          "product_cost_unit": 4.3,
          "product_cost_total": 4.3,
          "gross_profit_before_shipping_ads": 13.04,
          "margin_before_shipping_ads_pct": 75.2,
          "cost_source": "shopify_unit_cost",
          "cost_status": "matched",
          "cost_match_key": "58085095440733"
        }
      ],
      "cost_sources": [
        "shopify_unit_cost"
      ],
      "warnings": [
        "bol_ads_allocated_by_bol_revenue_share"
      ]
    },
    {
      "order_number": "#3dts1654",
      "date": "2026-06-24T19:17:18Z",
      "channel_source": "340764327937",
      "channel": "Onbekend/overig",
      "channel_reason": "source_not_classified",
      "customer_country_code": "NO",
      "customer_country": "Norway",
      "tags": [
        "Etsy",
        "Etsy order 4097516788",
        "VOEC"
      ],
      "payment_status": "PAID",
      "fulfillment_status": "FULFILLED",
      "landing_site": null,
      "referring_site": null,
      "omzet": 39.94,
      "verzendkosten_betaald_door_klant": 15,
      "verzendopbrengst_uit_pseudo_producten": 15,
      "werkelijke_verzendkosten": 12.1,
      "productkostprijs": 3.87,
      "korting": 0,
      "bruto_winst": 23.97,
      "bol_commissie": 0,
      "advertentiekosten": 5.83,
      "advertentiekosten_methode": "allocated_by_order_revenue_share",
      "bol_advertentiekosten": 0,
      "bol_advertentiekosten_methode": "none",
      "nettowinst": 18.14,
      "betrouwbare_nettowinst": 18.14,
      "geschatte_onvolledige_nettowinst": 0,
      "profit_reliability": "reliable",
      "cost_coverage": "shopify",
      "nettowinst_pct": 45.42,
      "bol_order_id": null,
      "bol_match_method": null,
      "bol_match_confidence": null,
      "eans": [],
      "line_items": [
        {
          "product_name": "Wandhouder Makita DC18RC Oplader",
          "variant_id": "57512098234717",
          "sku": "dc18rc3dts.shop",
          "ean": "8721516390011",
          "quantity": 1,
          "item_type": "product",
          "product_sale_price": 24.94,
          "line_revenue": 24.94,
          "product_cost_unit": 3.87,
          "product_cost_total": 3.87,
          "gross_profit_before_shipping_ads": 21.07,
          "margin_before_shipping_ads_pct": 84.48,
          "cost_source": "shopify_unit_cost",
          "cost_status": "matched",
          "cost_match_key": "57512098234717"
        },
        {
          "product_name": "Etsy Standard Shipping",
          "variant_id": null,
          "sku": "ETSY-SHIPPING",
          "ean": null,
          "quantity": 1,
          "item_type": "shipping_revenue",
          "product_sale_price": 15,
          "line_revenue": 15,
          "product_cost_unit": 0,
          "product_cost_total": 0,
          "gross_profit_before_shipping_ads": 15,
          "margin_before_shipping_ads_pct": null,
          "cost_source": "not_required_shipping_revenue",
          "cost_status": "not_required",
          "cost_match_key": "pseudo_product_exclusion"
        }
      ],
      "cost_sources": [
        "shopify_unit_cost"
      ],
      "warnings": [
        "ad_cost_allocated_by_revenue_share"
      ]
    },
    {
      "order_number": "#3dts1655",
      "date": "2026-06-24T19:23:22Z",
      "channel_source": "web",
      "channel": "Shopify direct",
      "channel_reason": "shopify_source_web",
      "customer_country_code": "NL",
      "customer_country": "Netherlands",
      "tags": [],
      "payment_status": "PAID",
      "fulfillment_status": "FULFILLED",
      "landing_site": null,
      "referring_site": null,
      "omzet": 14.6,
      "verzendkosten_betaald_door_klant": 4.65,
      "verzendopbrengst_uit_pseudo_producten": 0,
      "werkelijke_verzendkosten": 3.7,
      "productkostprijs": 3.07,
      "korting": 0,
      "bruto_winst": 7.83,
      "bol_commissie": 0,
      "advertentiekosten": 2.13,
      "advertentiekosten_methode": "allocated_by_order_revenue_share",
      "bol_advertentiekosten": 0,
      "bol_advertentiekosten_methode": "none",
      "nettowinst": 5.7,
      "betrouwbare_nettowinst": 5.7,
      "geschatte_onvolledige_nettowinst": 0,
      "profit_reliability": "reliable",
      "cost_coverage": "shopify",
      "nettowinst_pct": 39.04,
      "bol_order_id": null,
      "bol_match_method": null,
      "bol_match_confidence": null,
      "eans": [],
      "line_items": [
        {
          "product_name": "UniFi Cloud Key Gen2 Plus Verhoogde Wallmount",
          "variant_id": "63992391369053",
          "sku": "cloudkeygen23DTS.SHOP",
          "ean": "8721516390615",
          "quantity": 1,
          "item_type": "product",
          "product_sale_price": 9.95,
          "line_revenue": 9.95,
          "product_cost_unit": 3.07,
          "product_cost_total": 3.07,
          "gross_profit_before_shipping_ads": 6.88,
          "margin_before_shipping_ads_pct": 69.15,
          "cost_source": "shopify_unit_cost",
          "cost_status": "matched",
          "cost_match_key": "63992391369053"
        }
      ],
      "cost_sources": [
        "shopify_unit_cost"
      ],
      "warnings": [
        "ad_cost_allocated_by_revenue_share"
      ]
    },
    {
      "order_number": "#3dts1656",
      "date": "2026-06-25T08:30:57Z",
      "channel_source": "bol",
      "channel": "Bol via Shopify",
      "channel_reason": "matched_bol_retailer_api",
      "customer_country_code": "NL",
      "customer_country": "Netherlands",
      "tags": [
        "bol-cancel-accepted",
        "bol-geannuleerd",
        "bol.com"
      ],
      "payment_status": "PAID",
      "fulfillment_status": "UNFULFILLED",
      "landing_site": null,
      "referring_site": null,
      "omzet": 12.36,
      "verzendkosten_betaald_door_klant": 0,
      "verzendopbrengst_uit_pseudo_producten": 0,
      "werkelijke_verzendkosten": 3.7,
      "productkostprijs": 2.6,
      "korting": 0,
      "bruto_winst": 6.06,
      "bol_commissie": 0.85,
      "advertentiekosten": 0,
      "advertentiekosten_methode": "none",
      "bol_advertentiekosten": 0.49,
      "bol_advertentiekosten_methode": "allocated_by_bol_order_revenue_share",
      "nettowinst": 4.72,
      "betrouwbare_nettowinst": 4.72,
      "geschatte_onvolledige_nettowinst": 0,
      "profit_reliability": "reliable",
      "cost_coverage": "shopify",
      "nettowinst_pct": 38.19,
      "bol_order_id": "C0007DKH70",
      "bol_match_method": "date_amount_country_product_fallback",
      "bol_match_confidence": 0.9,
      "eans": [
        "9504822112282"
      ],
      "line_items": [
        {
          "product_name": "Wandbeugel UniFi AC Lite / nanoHD / AC LR / U6 Lite",
          "variant_id": "57838610743645",
          "sku": "Unifimountlite3DTS.shop",
          "ean": "08721516390042",
          "quantity": 1,
          "item_type": "product",
          "product_sale_price": 12.36,
          "line_revenue": 12.36,
          "product_cost_unit": 2.6,
          "product_cost_total": 2.6,
          "gross_profit_before_shipping_ads": 9.76,
          "margin_before_shipping_ads_pct": 78.96,
          "cost_source": "shopify_unit_cost",
          "cost_status": "matched",
          "cost_match_key": "57838610743645"
        }
      ],
      "cost_sources": [
        "shopify_unit_cost"
      ],
      "warnings": [
        "bol_ads_allocated_by_bol_revenue_share"
      ]
    },
    {
      "order_number": "#3dts1657",
      "date": "2026-06-25T19:15:49Z",
      "channel_source": "bol",
      "channel": "Bol via Shopify",
      "channel_reason": "matched_bol_retailer_api",
      "customer_country_code": "NL",
      "customer_country": "Netherlands",
      "tags": [
        "bol.com"
      ],
      "payment_status": "PAID",
      "fulfillment_status": "FULFILLED",
      "landing_site": null,
      "referring_site": null,
      "omzet": 36.98,
      "verzendkosten_betaald_door_klant": 0,
      "verzendopbrengst_uit_pseudo_producten": 0,
      "werkelijke_verzendkosten": 5.6,
      "productkostprijs": 10.7,
      "korting": 0,
      "bruto_winst": 20.68,
      "bol_commissie": 6.51,
      "advertentiekosten": 0,
      "advertentiekosten_methode": "none",
      "bol_advertentiekosten": 1.46,
      "bol_advertentiekosten_methode": "allocated_by_bol_order_revenue_share",
      "nettowinst": 12.71,
      "betrouwbare_nettowinst": 12.71,
      "geschatte_onvolledige_nettowinst": 0,
      "profit_reliability": "reliable",
      "cost_coverage": "shopify",
      "nettowinst_pct": 34.37,
      "bol_order_id": "C0007FK7L2",
      "bol_match_method": "identifier_or_sku_tag_source",
      "bol_match_confidence": 0.95,
      "eans": [
        "9503425233318"
      ],
      "line_items": [
        {
          "product_name": "3D-geprinte acculaderhouder voor Bosch 4A fietsoplader – wandmontage - BPC3400",
          "variant_id": "58800397255005",
          "sku": "Bosch4a-3DTS",
          "ean": "9503425233318",
          "quantity": 2,
          "item_type": "product",
          "product_sale_price": 18.49,
          "line_revenue": 36.98,
          "product_cost_unit": 5.35,
          "product_cost_total": 10.7,
          "gross_profit_before_shipping_ads": 26.28,
          "margin_before_shipping_ads_pct": 71.07,
          "cost_source": "shopify_unit_cost",
          "cost_status": "matched",
          "cost_match_key": "58800397255005"
        }
      ],
      "cost_sources": [
        "shopify_unit_cost"
      ],
      "warnings": [
        "bol_ads_allocated_by_bol_revenue_share"
      ]
    },
    {
      "order_number": "#3dts1658",
      "date": "2026-06-26T13:00:49Z",
      "channel_source": "bol",
      "channel": "Bol via Shopify",
      "channel_reason": "matched_bol_retailer_api",
      "customer_country_code": "NL",
      "customer_country": "Netherlands",
      "tags": [
        "bol.com"
      ],
      "payment_status": "PAID",
      "fulfillment_status": "UNFULFILLED",
      "landing_site": null,
      "referring_site": null,
      "omzet": 12.75,
      "verzendkosten_betaald_door_klant": 0,
      "verzendopbrengst_uit_pseudo_producten": 0,
      "werkelijke_verzendkosten": 3.7,
      "productkostprijs": 3.07,
      "korting": 0,
      "bruto_winst": 5.98,
      "bol_commissie": 0.87,
      "advertentiekosten": 0,
      "advertentiekosten_methode": "none",
      "bol_advertentiekosten": 0.5,
      "bol_advertentiekosten_methode": "allocated_by_bol_order_revenue_share",
      "nettowinst": 4.61,
      "betrouwbare_nettowinst": 4.61,
      "geschatte_onvolledige_nettowinst": 0,
      "profit_reliability": "reliable",
      "cost_coverage": "shopify",
      "nettowinst_pct": 36.16,
      "bol_order_id": "C0007HD15W",
      "bol_match_method": "date_amount_country_product_fallback",
      "bol_match_confidence": 0.9,
      "eans": [
        "9504237317951"
      ],
      "line_items": [
        {
          "product_name": "Montagebeugel passend voor UniFi UAP AC Pro",
          "variant_id": "58406162334045",
          "sku": "584061623340_133C",
          "ean": "8721516390196",
          "quantity": 1,
          "item_type": "product",
          "product_sale_price": 12.75,
          "line_revenue": 12.75,
          "product_cost_unit": 3.07,
          "product_cost_total": 3.07,
          "gross_profit_before_shipping_ads": 9.68,
          "margin_before_shipping_ads_pct": 75.92,
          "cost_source": "shopify_unit_cost",
          "cost_status": "matched",
          "cost_match_key": "58406162334045"
        }
      ],
      "cost_sources": [
        "shopify_unit_cost"
      ],
      "warnings": [
        "bol_ads_allocated_by_bol_revenue_share"
      ]
    },
    {
      "order_number": "#3dts1659",
      "date": "2026-06-26T17:07:42Z",
      "channel_source": "web",
      "channel": "Shopify direct",
      "channel_reason": "shopify_source_web",
      "customer_country_code": "FR",
      "customer_country": "France",
      "tags": [],
      "payment_status": "PAID",
      "fulfillment_status": "FULFILLED",
      "landing_site": null,
      "referring_site": null,
      "omzet": 23.9,
      "verzendkosten_betaald_door_klant": 12.95,
      "verzendopbrengst_uit_pseudo_producten": 0,
      "werkelijke_verzendkosten": 11.85,
      "productkostprijs": 4.3,
      "korting": 0,
      "bruto_winst": 7.75,
      "bol_commissie": 0,
      "advertentiekosten": 3.49,
      "advertentiekosten_methode": "allocated_by_order_revenue_share",
      "bol_advertentiekosten": 0,
      "bol_advertentiekosten_methode": "none",
      "nettowinst": 4.26,
      "betrouwbare_nettowinst": 4.26,
      "geschatte_onvolledige_nettowinst": 0,
      "profit_reliability": "reliable",
      "cost_coverage": "shopify",
      "nettowinst_pct": 17.82,
      "bol_order_id": null,
      "bol_match_method": null,
      "bol_match_confidence": null,
      "eans": [],
      "line_items": [
        {
          "product_name": "UniFi Access Point Wandbeugel – Verstelbare / Kantelbare Mount – Geschikt voor UAP-AC-LR, U6-LR, U6-Lite & U7-Lite",
          "variant_id": "63739025588573",
          "sku": "Unifikant3DTS.shop",
          "ean": "8721516390592",
          "quantity": 1,
          "item_type": "product",
          "product_sale_price": 10.95,
          "line_revenue": 10.95,
          "product_cost_unit": 4.3,
          "product_cost_total": 4.3,
          "gross_profit_before_shipping_ads": 6.65,
          "margin_before_shipping_ads_pct": 60.73,
          "cost_source": "shopify_unit_cost",
          "cost_status": "matched",
          "cost_match_key": "63739025588573"
        }
      ],
      "cost_sources": [
        "shopify_unit_cost"
      ],
      "warnings": [
        "ad_cost_allocated_by_revenue_share"
      ]
    },
    {
      "order_number": "#3dts1660",
      "date": "2026-06-26T20:15:53Z",
      "channel_source": "bol",
      "channel": "Bol via Shopify",
      "channel_reason": "matched_bol_retailer_api",
      "customer_country_code": "NL",
      "customer_country": "Netherlands",
      "tags": [
        "bol.com"
      ],
      "payment_status": "PAID",
      "fulfillment_status": "FULFILLED",
      "landing_site": null,
      "referring_site": null,
      "omzet": 12.36,
      "verzendkosten_betaald_door_klant": 0,
      "verzendopbrengst_uit_pseudo_producten": 0,
      "werkelijke_verzendkosten": 3.7,
      "productkostprijs": 2.6,
      "korting": 0,
      "bruto_winst": 6.06,
      "bol_commissie": 0.85,
      "advertentiekosten": 0,
      "advertentiekosten_methode": "none",
      "bol_advertentiekosten": 0.49,
      "bol_advertentiekosten_methode": "allocated_by_bol_order_revenue_share",
      "nettowinst": 4.72,
      "betrouwbare_nettowinst": 4.72,
      "geschatte_onvolledige_nettowinst": 0,
      "profit_reliability": "reliable",
      "cost_coverage": "shopify",
      "nettowinst_pct": 38.19,
      "bol_order_id": "C0007HWT86",
      "bol_match_method": "date_amount_country_product_fallback",
      "bol_match_confidence": 0.9,
      "eans": [
        "9504822112282"
      ],
      "line_items": [
        {
          "product_name": "Wandbeugel UniFi AC Lite / nanoHD / AC LR / U6 Lite",
          "variant_id": "57838610743645",
          "sku": "Unifimountlite3DTS.shop",
          "ean": "08721516390042",
          "quantity": 1,
          "item_type": "product",
          "product_sale_price": 12.36,
          "line_revenue": 12.36,
          "product_cost_unit": 2.6,
          "product_cost_total": 2.6,
          "gross_profit_before_shipping_ads": 9.76,
          "margin_before_shipping_ads_pct": 78.96,
          "cost_source": "shopify_unit_cost",
          "cost_status": "matched",
          "cost_match_key": "57838610743645"
        }
      ],
      "cost_sources": [
        "shopify_unit_cost"
      ],
      "warnings": [
        "bol_ads_allocated_by_bol_revenue_share"
      ]
    },
    {
      "order_number": "#3dts1661",
      "date": "2026-06-28T06:52:27Z",
      "channel_source": "web",
      "channel": "Shopify direct",
      "channel_reason": "shopify_source_web",
      "customer_country_code": "BE",
      "customer_country": "Belgium",
      "tags": [],
      "payment_status": "PAID",
      "fulfillment_status": "UNFULFILLED",
      "landing_site": "https://3dts.shop/products/wandhouder-schuin-voor-makita-dc18rd-duo-oplader-3d-geprint-compatibel-met-18v-laadstation",
      "referring_site": "https://www.google.com/",
      "omzet": 20.9,
      "verzendkosten_betaald_door_klant": 8.95,
      "verzendopbrengst_uit_pseudo_producten": 0,
      "werkelijke_verzendkosten": 8.09,
      "productkostprijs": 4.3,
      "korting": 0,
      "bruto_winst": 8.51,
      "bol_commissie": 0,
      "advertentiekosten": 3.05,
      "advertentiekosten_methode": "allocated_by_order_revenue_share",
      "bol_advertentiekosten": 0,
      "bol_advertentiekosten_methode": "none",
      "nettowinst": 5.46,
      "betrouwbare_nettowinst": 5.46,
      "geschatte_onvolledige_nettowinst": 0,
      "profit_reliability": "reliable",
      "cost_coverage": "shopify",
      "nettowinst_pct": 26.12,
      "bol_order_id": null,
      "bol_match_method": null,
      "bol_match_confidence": null,
      "eans": [],
      "line_items": [
        {
          "product_name": "Wandhouder voor Makita DC18RD Duo Oplader – 3D Geprint – Compatibel met 18V Laadstation",
          "variant_id": "58085095440733",
          "sku": "dc18rd3dts.shop",
          "ean": "8721516390004",
          "quantity": 1,
          "item_type": "product",
          "product_sale_price": 11.95,
          "line_revenue": 11.95,
          "product_cost_unit": 4.3,
          "product_cost_total": 4.3,
          "gross_profit_before_shipping_ads": 7.65,
          "margin_before_shipping_ads_pct": 64.02,
          "cost_source": "shopify_unit_cost",
          "cost_status": "matched",
          "cost_match_key": "58085095440733"
        }
      ],
      "cost_sources": [
        "shopify_unit_cost"
      ],
      "warnings": [
        "ad_cost_allocated_by_revenue_share"
      ]
    }
  ]
}
